EstymaApiWrapper/CustomErrors.py
EstymaApiWrapper/EstymaApi.py
EstymaApiWrapper/__init__.py
EstymaApiWrapper/api_translation_table.json
EstymaApiWrapper/languageTable.json
EstymaApiWrapper-0.0.69.dist-info/LICENSE
EstymaApiWrapper-0.0.69.dist-info/METADATA
EstymaApiWrapper-0.0.69.dist-info/WHEEL
EstymaApiWrapper-0.0.69.dist-info/top_level.txt
EstymaApiWrapper-0.0.69.dist-info/RECORD
