Metadata-Version: 2.1
Name: EstymaApiWrapper
Version: 0.0.69
Summary: Wrapper for the EstymaApi
Home-page: https://github.com/Tabisch/EstymaApi
Author: Tabisch
Author-email: tobithieman@gmail.com
Project-URL: Bug Tracker, https://github.com/Tabisch/EstymaApi/issues
Classifier: Programming Language :: Python :: 3
Classifier: License :: OSI Approved :: MIT License
Classifier: Operating System :: OS Independent
Requires-Python: >=3.11
License-File: LICENSE
